README.md
setup.py
dimond/__init__.py
laurel/__init__.py
laurel.egg-info/PKG-INFO
laurel.egg-info/SOURCES.txt
laurel.egg-info/dependency_links.txt
laurel.egg-info/not-zip-safe
laurel.egg-info/requires.txt
laurel.egg-info/top_level.txt