Metadata-Version: 1.1
Name: laurel
Version: 0.3
Summary: Python control of C by GE Bluetooth lightbulbs
Home-page: http://github.com/google/python-laurel
Author: Matthew Garrett
Author-email: mjg59@google.com
License: UNKNOWN
Platform: UNKNOWN
Classifier: Development Status :: 4 - Beta
Classifier: Intended Audience :: Developers
Classifier: License :: OSI Approved :: Apache Software License
Classifier: Operating System :: OS Independent
Classifier: Programming Language :: Python
